exploit_patterns/__init__.py
exploit_patterns-1.0.0.data/scripts/pattern_create
exploit_patterns-1.0.0.data/scripts/pattern_offset
exploit_patterns-1.0.0.dist-info/LICENSE
exploit_patterns-1.0.0.dist-info/METADATA
exploit_patterns-1.0.0.dist-info/WHEEL
exploit_patterns-1.0.0.dist-info/top_level.txt
exploit_patterns-1.0.0.dist-info/RECORD
