Metadata-Version: 2.1
Name: exploit-patterns
Version: 1.0.0
Summary: pattern_create and pattern_offset
Home-page: http://pypi.python.org/pypi/exploit-patterns/
Author: Philippe Grégoire
Author-email: git@pgregoire.xyz
License: LICENSE
Platform: UNKNOWN
